dffml_model_spacy/__init__.py
dffml_model_spacy/version.py
tests/__init__.py
tests/test_ner_integration.py
tests/test_ner_model.py
dffml_model_spacy-0.1.0.post0.dist-info/LICENSE
dffml_model_spacy-0.1.0.post0.dist-info/METADATA
dffml_model_spacy-0.1.0.post0.dist-info/WHEEL
dffml_model_spacy-0.1.0.post0.dist-info/entry_points.txt
dffml_model_spacy-0.1.0.post0.dist-info/top_level.txt
dffml_model_spacy-0.1.0.post0.dist-info/RECORD
