Metadata-Version: 2.1
Name: dffml-model-spacy
Version: 0.1.0.post0
Summary: DFFML model dffml-model-spacy
Home-page: https://github.com/intel/dffml/blob/master/model/spacy/README.md
Author: 0dust
Author-email: himanshutripathi366@gmail.com
Maintainer: 0dust
Maintainer-email: himanshutripathi366@gmail.com
License: MIT
Keywords: dffml
Platform: UNKNOWN
Classifier: Development Status :: 3 - Alpha
Classifier: Intended Audience :: Developers
Classifier: License :: OSI Approved :: MIT License
Classifier: Natural Language :: English
Classifier: Operating System :: OS Independent
Classifier: Programming Language :: Python :: 3 :: Only
Classifier: Programming Language :: Python :: 3.7
Classifier: Programming Language :: Python :: Implementation :: CPython
Classifier: Programming Language :: Python :: Implementation :: PyPy
License-File: LICENSE
Requires-Dist: dffml (>=0.4.0)
Requires-Dist: spacy (>=3.0.2)
